LICENSE
MANIFEST.in
README.rst
setup.py
sample/__init__.py
sample/algorithms.py
sample/file_input.py
sample/main.py
sample_cli.egg-info/PKG-INFO
sample_cli.egg-info/SOURCES.txt
sample_cli.egg-info/dependency_links.txt
sample_cli.egg-info/entry_points.txt
sample_cli.egg-info/top_level.txt