Metadata-Version: 1.0
Name: sample-cli
Version: 0.0.1
Summary: Command-line interface for sampling lines from text files
Home-page: UNKNOWN
Author: Paul Butler
Author-email: paulgb@gmail.com
License: UNKNOWN
Platform: UNKNOWN
